tenma_ps/__init__.py
tenma_ps/power_supply.py
tenma_ps/ps_fastapi.py
tenma_ps/ps_gui.py
tenma_ps-26.0.0.dist-info/WHEEL
tenma_ps-26.0.0.dist-info/METADATA
tenma_ps-26.0.0.dist-info/RECORD
