Metadata-Version: 2.3
Name: tenma-ps
Version: 26.0.0
Summary: python package for controlling tenma power supply
Keywords: python,tenma,power,supply,application
Author: chaitu-ycr
Author-email: chaitu-ycr <chaitu.ycr@gmail.com>
License: MIT License
Classifier: Programming Language :: Python :: 3
Classifier: License :: OSI Approved :: MIT License
Classifier: Operating System :: Microsoft :: Windows
Requires-Dist: tenma-serial
Requires-Dist: customtkinter
Requires-Dist: fastapi[all]
Requires-Python: >=3.10, <=3.14
Project-URL: homepage, https://github.com/chaitu-ycr/tenma-ps
Project-URL: repository, https://github.com/chaitu-ycr/tenma-ps
Project-URL: documentation, https://chaitu-ycr.github.io/tenma-ps
